{
  "etf": "XLP",
  "sector_name": "Conso. Essentiels",
  "sector_color": "#06b6d4",
  "date": "2026-04-08",
  "stocks": [
    {
      "id": "BF-B",
      "name": "BF-B",
      "return_5d": 0.01283,
      "return_20d": 0.10859,
      "volume_ratio": 0.33,
      "momentum_phase": "leading",
      "phase_value": 100.0,
      "phase_delta": 0.0,
      "rs_ratio": 107.9,
      "rs_momentum": 116.9,
      "rsi": 77.6,
      "sector_relative": "laggard",
      "days_in_phase": 5,
      "previous_phase": "lagging",
      "weight": 6.9
    },
    {
      "id": "MDLZ",
      "name": "MDLZ",
      "return_5d": 0.03084,
      "return_20d": 0.07188,
      "volume_ratio": 0.75,
      "momentum_phase": "leading",
      "phase_value": 96.3,
      "phase_delta": 3.4,
      "rs_ratio": 103.1,
      "rs_momentum": 106.2,
      "rsi": 71.8,
      "sector_relative": "leader",
      "days_in_phase": 12,
      "previous_phase": "lagging",
      "weight": 24.4
    },
    {
      "id": "TSN",
      "name": "TSN",
      "return_5d": 0.00544,
      "return_20d": 0.08092,
      "volume_ratio": 0.81,
      "momentum_phase": "leading",
      "phase_value": 93.6,
      "phase_delta": -6.4,
      "rs_ratio": 103.4,
      "rs_momentum": 105.3,
      "rsi": 66.0,
      "sector_relative": "laggard",
      "days_in_phase": 8,
      "previous_phase": "lagging",
      "weight": 7.6
    },
    {
      "id": "TAP",
      "name": "TAP",
      "return_5d": 0.02331,
      "return_20d": -0.02379,
      "volume_ratio": 0.89,
      "momentum_phase": "leading",
      "phase_value": 86.2,
      "phase_delta": 10.1,
      "rs_ratio": 101.7,
      "rs_momentum": 105.6,
      "rsi": 61.2,
      "sector_relative": "leader",
      "days_in_phase": 4,
      "previous_phase": "lagging",
      "weight": 4.9
    },
    {
      "id": "KHC",
      "name": "KHC",
      "return_5d": 0.03053,
      "return_20d": -0.00821,
      "volume_ratio": 0.91,
      "momentum_phase": "leading",
      "phase_value": 67.9,
      "phase_delta": 4.9,
      "rs_ratio": 102.3,
      "rs_momentum": 101.3,
      "rsi": 60.1,
      "sector_relative": "leader",
      "days_in_phase": 3,
      "previous_phase": "lagging",
      "weight": 15.2
    },
    {
      "id": "COST",
      "name": "COST",
      "return_5d": 0.03383,
      "return_20d": 0.03834,
      "volume_ratio": 1.38,
      "momentum_phase": "leading",
      "phase_value": 67.2,
      "phase_delta": 5.3,
      "rs_ratio": 103.1,
      "rs_momentum": 100.4,
      "rsi": 78.1,
      "sector_relative": "leader",
      "days_in_phase": 23,
      "previous_phase": "lagging",
      "weight": 66.7
    },
    {
      "id": "WMT",
      "name": "WMT",
      "return_5d": 0.0202,
      "return_20d": 0.03264,
      "volume_ratio": 0.99,
      "momentum_phase": "leading",
      "phase_value": 67.2,
      "phase_delta": -0.9,
      "rs_ratio": 102.3,
      "rs_momentum": 101.1,
      "rsi": 63.0,
      "sector_relative": "leader",
      "days_in_phase": 12,
      "previous_phase": "lagging",
      "weight": 100.0
    },
    {
      "id": "KO",
      "name": "KO",
      "return_5d": 0.0159,
      "return_20d": 0.00247,
      "volume_ratio": 0.82,
      "momentum_phase": "leading",
      "phase_value": 53.2,
      "phase_delta": -4.2,
      "rs_ratio": 100.8,
      "rs_momentum": 99.8,
      "rsi": 57.5,
      "sector_relative": "laggard",
      "days_in_phase": 46,
      "previous_phase": "improving",
      "weight": 46.1
    },
    {
      "id": "CPB",
      "name": "CPB",
      "return_5d": -0.05912,
      "return_20d": -0.08209,
      "volume_ratio": 0.86,
      "momentum_phase": "leading",
      "phase_value": 50.1,
      "phase_delta": -38.5,
      "rs_ratio": 96.9,
      "rs_momentum": 103.1,
      "rsi": 49.7,
      "sector_relative": "laggard",
      "days_in_phase": 3,
      "previous_phase": "lagging",
      "weight": 9.2
    },
    {
      "id": "BG",
      "name": "BG",
      "return_5d": -0.00912,
      "return_20d": 0.0361,
      "volume_ratio": 0.85,
      "momentum_phase": "leading",
      "phase_value": 46.4,
      "phase_delta": -53.6,
      "rs_ratio": 100.9,
      "rs_momentum": 98.4,
      "rsi": 56.4,
      "sector_relative": "laggard",
      "days_in_phase": 19,
      "previous_phase": "weakening",
      "weight": 10.1
    },
    {
      "id": "PEP",
      "name": "PEP",
      "return_5d": 0.00097,
      "return_20d": -0.03341,
      "volume_ratio": 1.07,
      "momentum_phase": "leading",
      "phase_value": 42.1,
      "phase_delta": -20.3,
      "rs_ratio": 99.5,
      "rs_momentum": 99.0,
      "rsi": 52.8,
      "sector_relative": "laggard",
      "days_in_phase": 3,
      "previous_phase": "lagging",
      "weight": 38.3
    },
    {
      "id": "STZ",
      "name": "STZ",
      "return_5d": -0.00549,
      "return_20d": 0.002,
      "volume_ratio": 1.9,
      "momentum_phase": "leading",
      "phase_value": 41.2,
      "phase_delta": -27.5,
      "rs_ratio": 98.7,
      "rs_momentum": 99.5,
      "rsi": 45.5,
      "sector_relative": "laggard",
      "days_in_phase": 16,
      "previous_phase": "lagging",
      "weight": 12.0
    },
    {
      "id": "ADM",
      "name": "ADM",
      "return_5d": -0.00898,
      "return_20d": 0.01257,
      "volume_ratio": 0.81,
      "momentum_phase": "leading",
      "phase_value": 27.8,
      "phase_delta": -69.1,
      "rs_ratio": 99.9,
      "rs_momentum": 95.7,
      "rsi": 52.6,
      "sector_relative": "laggard",
      "days_in_phase": 21,
      "previous_phase": "lagging",
      "weight": 13.1
    },
    {
      "id": "KR",
      "name": "KR",
      "return_5d": 0.00595,
      "return_20d": -0.01704,
      "volume_ratio": 0.93,
      "momentum_phase": "leading",
      "phase_value": 0.0,
      "phase_delta": -50.7,
      "rs_ratio": 96.8,
      "rs_momentum": 90.7,
      "rsi": 42.3,
      "sector_relative": "laggard",
      "days_in_phase": 40,
      "previous_phase": "lagging",
      "weight": 18.4
    },
    {
      "id": "MNST",
      "name": "MNST",
      "return_5d": 0.03257,
      "return_20d": -0.0307,
      "volume_ratio": 1.06,
      "momentum_phase": "improving",
      "phase_value": 74.7,
      "phase_delta": 24.0,
      "rs_ratio": 100.8,
      "rs_momentum": 104.1,
      "rsi": 54.5,
      "sector_relative": "leader",
      "days_in_phase": 2,
      "previous_phase": "lagging",
      "weight": 15.4
    },
    {
      "id": "TGT",
      "name": "TGT",
      "return_5d": 0.02217,
      "return_20d": 0.03654,
      "volume_ratio": 0.63,
      "momentum_phase": "weakening",
      "phase_value": 57.2,
      "phase_delta": -7.1,
      "rs_ratio": 103.8,
      "rs_momentum": 97.6,
      "rsi": 69.5,
      "sector_relative": "leader",
      "days_in_phase": 2,
      "previous_phase": "leading",
      "weight": 27.8
    },
    {
      "id": "MO",
      "name": "MO",
      "return_5d": 0.02016,
      "return_20d": 0.02381,
      "volume_ratio": 1.02,
      "momentum_phase": "weakening",
      "phase_value": 56.7,
      "phase_delta": -1.6,
      "rs_ratio": 101.6,
      "rs_momentum": 99.8,
      "rsi": 67.1,
      "sector_relative": "leader",
      "days_in_phase": 11,
      "previous_phase": "leading",
      "weight": 27.9
    },
    {
      "id": "KMB",
      "name": "KMB",
      "return_5d": -0.00584,
      "return_20d": -0.03039,
      "volume_ratio": 1.39,
      "momentum_phase": "weakening",
      "phase_value": 43.0,
      "phase_delta": 2.2,
      "rs_ratio": 98.3,
      "rs_momentum": 100.3,
      "rsi": 45.0,
      "sector_relative": "laggard",
      "days_in_phase": 10,
      "previous_phase": "lagging",
      "weight": 19.9
    },
    {
      "id": "CLX",
      "name": "CLX",
      "return_5d": 0.01372,
      "return_20d": -0.05778,
      "volume_ratio": 1.21,
      "momentum_phase": "lagging",
      "phase_value": 56.1,
      "phase_delta": 33.9,
      "rs_ratio": 99.2,
      "rs_momentum": 102.0,
      "rsi": 45.0,
      "sector_relative": "laggard",
      "days_in_phase": 22,
      "previous_phase": "leading",
      "weight": 9.4
    },
    {
      "id": "CAG",
      "name": "CAG",
      "return_5d": 0.00387,
      "return_20d": -0.08245,
      "volume_ratio": 0.56,
      "momentum_phase": "lagging",
      "phase_value": 46.6,
      "phase_delta": 25.0,
      "rs_ratio": 98.5,
      "rs_momentum": 100.8,
      "rsi": 50.4,
      "sector_relative": "laggard",
      "days_in_phase": 29,
      "previous_phase": "leading",
      "weight": 11.0
    },
    {
      "id": "KVUE",
      "name": "KVUE",
      "return_5d": -0.0023,
      "return_20d": -0.01756,
      "volume_ratio": 0.84,
      "momentum_phase": "lagging",
      "phase_value": 42.7,
      "phase_delta": -2.3,
      "rs_ratio": 98.9,
      "rs_momentum": 99.7,
      "rsi": 46.7,
      "sector_relative": "laggard",
      "days_in_phase": 16,
      "previous_phase": "leading",
      "weight": 13.5
    },
    {
      "id": "CL",
      "name": "CL",
      "return_5d": 0.00164,
      "return_20d": -0.04531,
      "volume_ratio": 0.66,
      "momentum_phase": "lagging",
      "phase_value": 40.6,
      "phase_delta": 12.6,
      "rs_ratio": 98.7,
      "rs_momentum": 99.4,
      "rsi": 42.0,
      "sector_relative": "laggard",
      "days_in_phase": 18,
      "previous_phase": "leading",
      "weight": 22.0
    },
    {
      "id": "GIS",
      "name": "GIS",
      "return_5d": -0.01639,
      "return_20d": -0.09985,
      "volume_ratio": 0.86,
      "momentum_phase": "lagging",
      "phase_value": 39.5,
      "phase_delta": 6.6,
      "rs_ratio": 96.8,
      "rs_momentum": 101.1,
      "rsi": 40.1,
      "sector_relative": "laggard",
      "days_in_phase": 60,
      "previous_phase": null,
      "weight": 16.2
    },
    {
      "id": "DLTR",
      "name": "DLTR",
      "return_5d": -0.02833,
      "return_20d": -0.06737,
      "volume_ratio": 1.13,
      "momentum_phase": "lagging",
      "phase_value": 38.4,
      "phase_delta": -47.1,
      "rs_ratio": 96.9,
      "rs_momentum": 100.8,
      "rsi": 45.8,
      "sector_relative": "laggard",
      "days_in_phase": 12,
      "previous_phase": "improving",
      "weight": 13.6
    },
    {
      "id": "DG",
      "name": "DG",
      "return_5d": 0.05516,
      "return_20d": -0.14641,
      "volume_ratio": 0.62,
      "momentum_phase": "lagging",
      "phase_value": 38.3,
      "phase_delta": 38.3,
      "rs_ratio": 98.5,
      "rs_momentum": 99.1,
      "rsi": 45.3,
      "sector_relative": "leader",
      "days_in_phase": 15,
      "previous_phase": "leading",
      "weight": 18.5
    },
    {
      "id": "PG",
      "name": "PG",
      "return_5d": 0.00562,
      "return_20d": -0.05492,
      "volume_ratio": 0.96,
      "momentum_phase": "lagging",
      "phase_value": 38.3,
      "phase_delta": 3.3,
      "rs_ratio": 98.8,
      "rs_momentum": 98.8,
      "rsi": 44.0,
      "sector_relative": "laggard",
      "days_in_phase": 16,
      "previous_phase": "leading",
      "weight": 64.5
    },
    {
      "id": "PM",
      "name": "PM",
      "return_5d": 0.02295,
      "return_20d": -0.02675,
      "volume_ratio": 0.84,
      "momentum_phase": "lagging",
      "phase_value": 36.5,
      "phase_delta": -29.5,
      "rs_ratio": 97.3,
      "rs_momentum": 100.0,
      "rsi": 43.1,
      "sector_relative": "leader",
      "days_in_phase": 33,
      "previous_phase": "weakening",
      "weight": 31.3
    },
    {
      "id": "KDP",
      "name": "KDP",
      "return_5d": 0.00584,
      "return_20d": -0.05721,
      "volume_ratio": 0.83,
      "momentum_phase": "lagging",
      "phase_value": 34.3,
      "phase_delta": 0.0,
      "rs_ratio": 97.4,
      "rs_momentum": 99.5,
      "rsi": 37.0,
      "sector_relative": "laggard",
      "days_in_phase": 17,
      "previous_phase": "leading",
      "weight": 10.6
    },
    {
      "id": "HSY",
      "name": "HSY",
      "return_5d": 0.03007,
      "return_20d": -0.04067,
      "volume_ratio": 0.58,
      "momentum_phase": "lagging",
      "phase_value": 32.8,
      "phase_delta": 32.7,
      "rs_ratio": 97.8,
      "rs_momentum": 98.7,
      "rsi": 45.1,
      "sector_relative": "leader",
      "days_in_phase": 5,
      "previous_phase": "leading",
      "weight": 15.0
    },
    {
      "id": "CHD",
      "name": "CHD",
      "return_5d": 0.01454,
      "return_20d": -0.05488,
      "volume_ratio": 1.02,
      "momentum_phase": "lagging",
      "phase_value": 28.3,
      "phase_delta": 11.2,
      "rs_ratio": 98.6,
      "rs_momentum": 97.1,
      "rsi": 42.0,
      "sector_relative": "laggard",
      "days_in_phase": 14,
      "previous_phase": "weakening",
      "weight": 8.1
    },
    {
      "id": "HRL",
      "name": "HRL",
      "return_5d": -0.0177,
      "return_20d": -0.06036,
      "volume_ratio": 0.75,
      "momentum_phase": "lagging",
      "phase_value": 16.5,
      "phase_delta": -29.0,
      "rs_ratio": 95.6,
      "rs_momentum": 97.7,
      "rsi": 36.0,
      "sector_relative": "laggard",
      "days_in_phase": 2,
      "previous_phase": "improving",
      "weight": 3.7
    },
    {
      "id": "MKC",
      "name": "MKC",
      "return_5d": 0.04403,
      "return_20d": -0.15718,
      "volume_ratio": 0.86,
      "momentum_phase": "lagging",
      "phase_value": 14.1,
      "phase_delta": 14.1,
      "rs_ratio": 94.0,
      "rs_momentum": 98.8,
      "rsi": 35.3,
      "sector_relative": "leader",
      "days_in_phase": 19,
      "previous_phase": "leading",
      "weight": 10.7
    },
    {
      "id": "SYY",
      "name": "SYY",
      "return_5d": 0.04914,
      "return_20d": -0.10458,
      "volume_ratio": 0.85,
      "momentum_phase": "lagging",
      "phase_value": 9.0,
      "phase_delta": 9.0,
      "rs_ratio": 94.8,
      "rs_momentum": 97.0,
      "rsi": 35.6,
      "sector_relative": "leader",
      "days_in_phase": 20,
      "previous_phase": "weakening",
      "weight": 16.3
    },
    {
      "id": "EL",
      "name": "EL",
      "return_5d": 0.01032,
      "return_20d": -0.21958,
      "volume_ratio": 0.63,
      "momentum_phase": "lagging",
      "phase_value": 6.3,
      "phase_delta": 6.3,
      "rs_ratio": 91.7,
      "rs_momentum": 99.6,
      "rsi": 29.6,
      "sector_relative": "laggard",
      "days_in_phase": 46,
      "previous_phase": "weakening",
      "weight": 16.5
    },
    {
      "id": "SJM",
      "name": "SJM",
      "return_5d": -0.0178,
      "return_20d": -0.12851,
      "volume_ratio": 0.74,
      "momentum_phase": "lagging",
      "phase_value": 0.0,
      "phase_delta": 0.0,
      "rs_ratio": 94.4,
      "rs_momentum": 93.9,
      "rsi": 13.4,
      "sector_relative": "laggard",
      "days_in_phase": 15,
      "previous_phase": "leading",
      "weight": 7.0
    }
  ],
  "correlations": [
    {
      "source": "KMB",
      "target": "KVUE",
      "correlation": 0.99
    },
    {
      "source": "CL",
      "target": "PG",
      "correlation": 0.94
    },
    {
      "source": "BG",
      "target": "ADM",
      "correlation": 0.865
    },
    {
      "source": "CAG",
      "target": "GIS",
      "correlation": 0.863
    },
    {
      "source": "CPB",
      "target": "CAG",
      "correlation": 0.824
    },
    {
      "source": "WMT",
      "target": "KO",
      "correlation": 0.821
    },
    {
      "source": "CPB",
      "target": "GIS",
      "correlation": 0.819
    },
    {
      "source": "KO",
      "target": "PEP",
      "correlation": 0.797
    },
    {
      "source": "KO",
      "target": "PG",
      "correlation": 0.772
    },
    {
      "source": "KO",
      "target": "CL",
      "correlation": 0.742
    },
    {
      "source": "TGT",
      "target": "KMB",
      "correlation": 0.74
    },
    {
      "source": "TGT",
      "target": "CAG",
      "correlation": 0.738
    },
    {
      "source": "CLX",
      "target": "PG",
      "correlation": 0.738
    },
    {
      "source": "CLX",
      "target": "EL",
      "correlation": 0.733
    },
    {
      "source": "MDLZ",
      "target": "PG",
      "correlation": 0.728
    },
    {
      "source": "TGT",
      "target": "KVUE",
      "correlation": 0.721
    },
    {
      "source": "CLX",
      "target": "KDP",
      "correlation": 0.721
    },
    {
      "source": "MDLZ",
      "target": "CL",
      "correlation": 0.716
    },
    {
      "source": "CLX",
      "target": "CL",
      "correlation": 0.715
    },
    {
      "source": "KO",
      "target": "CHD",
      "correlation": 0.713
    }
  ]
}