{
  "etf": "XLU",
  "sector_name": "Services Publics",
  "sector_color": "#eab308",
  "date": "2026-04-20",
  "stocks": [
    {
      "id": "VST",
      "name": "VST",
      "return_5d": -0.02665,
      "return_20d": 0.05493,
      "volume_ratio": 0.77,
      "momentum_phase": "leading",
      "phase_value": 100.0,
      "phase_delta": 8.7,
      "rs_ratio": 103.3,
      "rs_momentum": 111.1,
      "rsi": 65.9,
      "sector_relative": "laggard",
      "days_in_phase": 2,
      "previous_phase": "improving",
      "weight": 74.0
    },
    {
      "id": "NRG",
      "name": "NRG",
      "return_5d": -0.0806,
      "return_20d": 0.03565,
      "volume_ratio": 1.56,
      "momentum_phase": "leading",
      "phase_value": 93.6,
      "phase_delta": -6.4,
      "rs_ratio": 101.1,
      "rs_momentum": 107.6,
      "rsi": 66.1,
      "sector_relative": "laggard",
      "days_in_phase": 6,
      "previous_phase": "lagging",
      "weight": 47.0
    },
    {
      "id": "CEG",
      "name": "CEG",
      "return_5d": -0.03051,
      "return_20d": -0.00759,
      "volume_ratio": 0.87,
      "momentum_phase": "leading",
      "phase_value": 81.7,
      "phase_delta": 22.3,
      "rs_ratio": 100.1,
      "rs_momentum": 106.2,
      "rsi": 43.2,
      "sector_relative": "laggard",
      "days_in_phase": 1,
      "previous_phase": "lagging",
      "weight": 100.0
    },
    {
      "id": "ETR",
      "name": "ETR",
      "return_5d": -0.01653,
      "return_20d": 0.12157,
      "volume_ratio": 1.06,
      "momentum_phase": "leading",
      "phase_value": 73.6,
      "phase_delta": -24.3,
      "rs_ratio": 102.2,
      "rs_momentum": 102.5,
      "rsi": 59.4,
      "sector_relative": "laggard",
      "days_in_phase": 15,
      "previous_phase": "weakening",
      "weight": 41.6
    },
    {
      "id": "AES",
      "name": "AES",
      "return_5d": 0.00556,
      "return_20d": 0.02841,
      "volume_ratio": 0.44,
      "momentum_phase": "leading",
      "phase_value": 69.6,
      "phase_delta": -28.6,
      "rs_ratio": 102.1,
      "rs_momentum": 101.9,
      "rsi": 87.1,
      "sector_relative": "leader",
      "days_in_phase": 2,
      "previous_phase": "lagging",
      "weight": 17.7
    },
    {
      "id": "XEL",
      "name": "XEL",
      "return_5d": 0.00614,
      "return_20d": 0.04379,
      "volume_ratio": 0.94,
      "momentum_phase": "leading",
      "phase_value": 68.9,
      "phase_delta": 17.3,
      "rs_ratio": 101.3,
      "rs_momentum": 102.5,
      "rsi": 55.0,
      "sector_relative": "leader",
      "days_in_phase": 8,
      "previous_phase": "lagging",
      "weight": 42.0
    },
    {
      "id": "NI",
      "name": "NI",
      "return_5d": 0.01186,
      "return_20d": 0.0508,
      "volume_ratio": 0.86,
      "momentum_phase": "leading",
      "phase_value": 67.0,
      "phase_delta": 21.9,
      "rs_ratio": 102.2,
      "rs_momentum": 101.2,
      "rsi": 61.4,
      "sector_relative": "leader",
      "days_in_phase": 24,
      "previous_phase": "lagging",
      "weight": 21.1
    },
    {
      "id": "AEP",
      "name": "AEP",
      "return_5d": -0.01609,
      "return_20d": 0.0419,
      "volume_ratio": 0.92,
      "momentum_phase": "leading",
      "phase_value": 63.0,
      "phase_delta": 4.5,
      "rs_ratio": 101.2,
      "rs_momentum": 101.4,
      "rsi": 58.3,
      "sector_relative": "laggard",
      "days_in_phase": 4,
      "previous_phase": "weakening",
      "weight": 44.8
    },
    {
      "id": "LNT",
      "name": "LNT",
      "return_5d": 0.00138,
      "return_20d": 0.0467,
      "volume_ratio": 0.93,
      "momentum_phase": "leading",
      "phase_value": 61.0,
      "phase_delta": 13.5,
      "rs_ratio": 101.4,
      "rs_momentum": 100.8,
      "rsi": 58.1,
      "sector_relative": "leader",
      "days_in_phase": 24,
      "previous_phase": "lagging",
      "weight": 16.1
    },
    {
      "id": "D",
      "name": "D",
      "return_5d": -0.02339,
      "return_20d": 0.04012,
      "volume_ratio": 0.58,
      "momentum_phase": "leading",
      "phase_value": 59.8,
      "phase_delta": -2.5,
      "rs_ratio": 100.7,
      "rs_momentum": 101.3,
      "rsi": 52.6,
      "sector_relative": "laggard",
      "days_in_phase": 8,
      "previous_phase": "improving",
      "weight": 30.0
    },
    {
      "id": "AEE",
      "name": "AEE",
      "return_5d": -0.00527,
      "return_20d": 0.04088,
      "volume_ratio": 0.73,
      "momentum_phase": "leading",
      "phase_value": 58.7,
      "phase_delta": 8.8,
      "rs_ratio": 101.1,
      "rs_momentum": 100.7,
      "rsi": 56.4,
      "sector_relative": "leader",
      "days_in_phase": 25,
      "previous_phase": "lagging",
      "weight": 19.8
    },
    {
      "id": "PPL",
      "name": "PPL",
      "return_5d": -0.02222,
      "return_20d": 0.04959,
      "volume_ratio": 0.75,
      "momentum_phase": "leading",
      "phase_value": 56.2,
      "phase_delta": -11.6,
      "rs_ratio": 101.1,
      "rs_momentum": 100.2,
      "rsi": 61.5,
      "sector_relative": "laggard",
      "days_in_phase": 27,
      "previous_phase": "lagging",
      "weight": 29.0
    },
    {
      "id": "CMS",
      "name": "CMS",
      "return_5d": -0.02258,
      "return_20d": 0.03243,
      "volume_ratio": 0.44,
      "momentum_phase": "leading",
      "phase_value": 43.3,
      "phase_delta": -7.6,
      "rs_ratio": 99.9,
      "rs_momentum": 98.7,
      "rsi": 49.0,
      "sector_relative": "laggard",
      "days_in_phase": 22,
      "previous_phase": "lagging",
      "weight": 24.6
    },
    {
      "id": "EIX",
      "name": "EIX",
      "return_5d": -0.02473,
      "return_20d": 0.01079,
      "volume_ratio": 0.7,
      "momentum_phase": "leading",
      "phase_value": 34.7,
      "phase_delta": -23.4,
      "rs_ratio": 98.7,
      "rs_momentum": 98.2,
      "rsi": 48.2,
      "sector_relative": "laggard",
      "days_in_phase": 10,
      "previous_phase": "weakening",
      "weight": 24.1
    },
    {
      "id": "FE",
      "name": "FE",
      "return_5d": -0.03115,
      "return_20d": 0.01394,
      "volume_ratio": 1.02,
      "momentum_phase": "leading",
      "phase_value": 32.5,
      "phase_delta": -15.4,
      "rs_ratio": 98.5,
      "rs_momentum": 98.0,
      "rsi": 39.5,
      "sector_relative": "laggard",
      "days_in_phase": 27,
      "previous_phase": "lagging",
      "weight": 23.1
    },
    {
      "id": "PEG",
      "name": "PEG",
      "return_5d": -0.01597,
      "return_20d": 0.01153,
      "volume_ratio": 0.55,
      "momentum_phase": "improving",
      "phase_value": 50.0,
      "phase_delta": 10.2,
      "rs_ratio": 99.8,
      "rs_momentum": 100.2,
      "rsi": 47.3,
      "sector_relative": "laggard",
      "days_in_phase": 17,
      "previous_phase": "lagging",
      "weight": 24.6
    },
    {
      "id": "PNW",
      "name": "PNW",
      "return_5d": 0.00253,
      "return_20d": 0.05514,
      "volume_ratio": 0.58,
      "momentum_phase": "weakening",
      "phase_value": 64.5,
      "phase_delta": 15.9,
      "rs_ratio": 102.0,
      "rs_momentum": 100.9,
      "rsi": 62.9,
      "sector_relative": "leader",
      "days_in_phase": 10,
      "previous_phase": "leading",
      "weight": 12.7
    },
    {
      "id": "EVRG",
      "name": "EVRG",
      "return_5d": -0.00305,
      "return_20d": 0.02846,
      "volume_ratio": 1.14,
      "momentum_phase": "weakening",
      "phase_value": 51.0,
      "phase_delta": 3.5,
      "rs_ratio": 100.3,
      "rs_momentum": 99.9,
      "rsi": 50.5,
      "sector_relative": "leader",
      "days_in_phase": 31,
      "previous_phase": "lagging",
      "weight": 15.5
    },
    {
      "id": "DTE",
      "name": "DTE",
      "return_5d": -0.01266,
      "return_20d": 0.02516,
      "volume_ratio": 0.52,
      "momentum_phase": "weakening",
      "phase_value": 45.2,
      "phase_delta": 3.4,
      "rs_ratio": 100.1,
      "rs_momentum": 98.9,
      "rsi": 49.2,
      "sector_relative": "leader",
      "days_in_phase": 10,
      "previous_phase": "leading",
      "weight": 17.1
    },
    {
      "id": "ATO",
      "name": "ATO",
      "return_5d": -0.01026,
      "return_20d": 0.02872,
      "volume_ratio": 0.45,
      "momentum_phase": "weakening",
      "phase_value": 44.4,
      "phase_delta": 3.7,
      "rs_ratio": 100.6,
      "rs_momentum": 98.3,
      "rsi": 52.9,
      "sector_relative": "leader",
      "days_in_phase": 7,
      "previous_phase": "leading",
      "weight": 17.8
    },
    {
      "id": "ES",
      "name": "ES",
      "return_5d": -0.00725,
      "return_20d": 0.01271,
      "volume_ratio": 0.6,
      "momentum_phase": "lagging",
      "phase_value": 74.7,
      "phase_delta": 36.8,
      "rs_ratio": 100.1,
      "rs_momentum": 104.8,
      "rsi": 50.8,
      "sector_relative": "leader",
      "days_in_phase": 18,
      "previous_phase": "leading",
      "weight": 18.6
    },
    {
      "id": "PCG",
      "name": "PCG",
      "return_5d": -0.01196,
      "return_20d": 0.00056,
      "volume_ratio": 0.78,
      "momentum_phase": "lagging",
      "phase_value": 47.0,
      "phase_delta": -1.9,
      "rs_ratio": 99.1,
      "rs_momentum": 100.3,
      "rsi": 48.6,
      "sector_relative": "leader",
      "days_in_phase": 28,
      "previous_phase": "leading",
      "weight": 46.0
    },
    {
      "id": "NEE",
      "name": "NEE",
      "return_5d": 0.00767,
      "return_20d": 0.01973,
      "volume_ratio": 0.61,
      "momentum_phase": "lagging",
      "phase_value": 44.5,
      "phase_delta": 2.8,
      "rs_ratio": 100.3,
      "rs_momentum": 98.6,
      "rsi": 49.7,
      "sector_relative": "leader",
      "days_in_phase": 2,
      "previous_phase": "leading",
      "weight": 89.5
    },
    {
      "id": "WEC",
      "name": "WEC",
      "return_5d": -0.01167,
      "return_20d": 0.02758,
      "volume_ratio": 0.51,
      "momentum_phase": "lagging",
      "phase_value": 43.8,
      "phase_delta": 1.5,
      "rs_ratio": 100.2,
      "rs_momentum": 98.6,
      "rsi": 49.2,
      "sector_relative": "leader",
      "days_in_phase": 3,
      "previous_phase": "leading",
      "weight": 24.1
    },
    {
      "id": "CNP",
      "name": "CNP",
      "return_5d": -0.00466,
      "return_20d": 0.02251,
      "volume_ratio": 0.81,
      "momentum_phase": "lagging",
      "phase_value": 41.9,
      "phase_delta": 15.0,
      "rs_ratio": 100.1,
      "rs_momentum": 98.3,
      "rsi": 46.9,
      "sector_relative": "leader",
      "days_in_phase": 5,
      "previous_phase": "leading",
      "weight": 20.2
    },
    {
      "id": "DUK",
      "name": "DUK",
      "return_5d": -0.01479,
      "return_20d": 0.00408,
      "volume_ratio": 0.75,
      "momentum_phase": "lagging",
      "phase_value": 30.9,
      "phase_delta": 1.0,
      "rs_ratio": 99.0,
      "rs_momentum": 97.2,
      "rsi": 33.1,
      "sector_relative": "leader",
      "days_in_phase": 5,
      "previous_phase": "leading",
      "weight": 55.1
    },
    {
      "id": "SO",
      "name": "SO",
      "return_5d": -0.02553,
      "return_20d": -0.00256,
      "volume_ratio": 0.48,
      "momentum_phase": "lagging",
      "phase_value": 26.2,
      "phase_delta": -3.7,
      "rs_ratio": 98.2,
      "rs_momentum": 97.0,
      "rsi": 26.9,
      "sector_relative": "laggard",
      "days_in_phase": 6,
      "previous_phase": "leading",
      "weight": 50.9
    },
    {
      "id": "ED",
      "name": "ED",
      "return_5d": -0.01782,
      "return_20d": 0.00513,
      "volume_ratio": 0.55,
      "momentum_phase": "lagging",
      "phase_value": 22.9,
      "phase_delta": -0.9,
      "rs_ratio": 98.4,
      "rs_momentum": 96.2,
      "rsi": 33.9,
      "sector_relative": "laggard",
      "days_in_phase": 5,
      "previous_phase": "leading",
      "weight": 24.0
    },
    {
      "id": "EXC",
      "name": "EXC",
      "return_5d": -0.04644,
      "return_20d": -0.01632,
      "volume_ratio": 1.15,
      "momentum_phase": "lagging",
      "phase_value": 18.2,
      "phase_delta": -3.5,
      "rs_ratio": 96.7,
      "rs_momentum": 97.0,
      "rsi": 25.9,
      "sector_relative": "laggard",
      "days_in_phase": 7,
      "previous_phase": "weakening",
      "weight": 41.9
    },
    {
      "id": "AWK",
      "name": "AWK",
      "return_5d": -0.00105,
      "return_20d": -0.01827,
      "volume_ratio": 0.89,
      "momentum_phase": "lagging",
      "phase_value": 18.1,
      "phase_delta": 8.8,
      "rs_ratio": 99.0,
      "rs_momentum": 94.6,
      "rsi": 38.1,
      "sector_relative": "leader",
      "days_in_phase": 6,
      "previous_phase": "leading",
      "weight": 30.7
    },
    {
      "id": "SRE",
      "name": "SRE",
      "return_5d": -0.02891,
      "return_20d": -0.00086,
      "volume_ratio": 0.9,
      "momentum_phase": "lagging",
      "phase_value": 11.3,
      "phase_delta": -25.6,
      "rs_ratio": 97.4,
      "rs_momentum": 94.9,
      "rsi": 37.3,
      "sector_relative": "laggard",
      "days_in_phase": 2,
      "previous_phase": "leading",
      "weight": 37.0
    }
  ],
  "correlations": [
    {
      "source": "CMS",
      "target": "WEC",
      "correlation": 0.933
    },
    {
      "source": "LNT",
      "target": "EVRG",
      "correlation": 0.911
    },
    {
      "source": "ATO",
      "target": "WEC",
      "correlation": 0.907
    },
    {
      "source": "AEE",
      "target": "EVRG",
      "correlation": 0.902
    },
    {
      "source": "CMS",
      "target": "DTE",
      "correlation": 0.902
    },
    {
      "source": "EVRG",
      "target": "DTE",
      "correlation": 0.897
    },
    {
      "source": "PPL",
      "target": "FE",
      "correlation": 0.896
    },
    {
      "source": "WEC",
      "target": "CNP",
      "correlation": 0.891
    },
    {
      "source": "XEL",
      "target": "AEE",
      "correlation": 0.887
    },
    {
      "source": "DUK",
      "target": "ED",
      "correlation": 0.883
    },
    {
      "source": "EIX",
      "target": "PCG",
      "correlation": 0.877
    },
    {
      "source": "CMS",
      "target": "FE",
      "correlation": 0.872
    },
    {
      "source": "CMS",
      "target": "SO",
      "correlation": 0.872
    },
    {
      "source": "ATO",
      "target": "DUK",
      "correlation": 0.871
    },
    {
      "source": "LNT",
      "target": "DTE",
      "correlation": 0.87
    },
    {
      "source": "CMS",
      "target": "ATO",
      "correlation": 0.866
    },
    {
      "source": "AEE",
      "target": "DTE",
      "correlation": 0.865
    },
    {
      "source": "CMS",
      "target": "ED",
      "correlation": 0.865
    },
    {
      "source": "WEC",
      "target": "ED",
      "correlation": 0.863
    },
    {
      "source": "LNT",
      "target": "ATO",
      "correlation": 0.862
    }
  ]
}