{
  "etf": "XLY",
  "sector_name": "Conso. Discretionnaire",
  "sector_color": "#f97316",
  "date": "2026-03-19",
  "stocks": [
    {
      "id": "AMZN",
      "name": "AMZN",
      "return_5d": 0.00525,
      "return_20d": -0.00643,
      "volume_ratio": 0.77,
      "momentum_phase": "leading",
      "phase_value": 100.0,
      "phase_delta": 0.0,
      "rs_ratio": 103.1,
      "rs_momentum": 109.1,
      "rsi": 48.4,
      "sector_relative": "leader",
      "days_in_phase": 9,
      "previous_phase": "lagging",
      "weight": 43.0
    },
    {
      "id": "BKNG",
      "name": "BKNG",
      "return_5d": 0.0125,
      "return_20d": 0.05575,
      "volume_ratio": 0.47,
      "momentum_phase": "leading",
      "phase_value": 100.0,
      "phase_delta": 0.0,
      "rs_ratio": 104.9,
      "rs_momentum": 117.7,
      "rsi": 52.5,
      "sector_relative": "leader",
      "days_in_phase": 9,
      "previous_phase": "lagging",
      "weight": 9.6
    },
    {
      "id": "EBAY",
      "name": "EBAY",
      "return_5d": -0.00657,
      "return_20d": 0.03376,
      "volume_ratio": 0.89,
      "momentum_phase": "leading",
      "phase_value": 100.0,
      "phase_delta": 0.0,
      "rs_ratio": 105.2,
      "rs_momentum": 106.8,
      "rsi": 50.5,
      "sector_relative": "leader",
      "days_in_phase": 11,
      "previous_phase": "lagging",
      "weight": 2.1
    },
    {
      "id": "EXPE",
      "name": "EXPE",
      "return_5d": 0.04834,
      "return_20d": 0.17913,
      "volume_ratio": 0.59,
      "momentum_phase": "leading",
      "phase_value": 100.0,
      "phase_delta": 0.0,
      "rs_ratio": 111.2,
      "rs_momentum": 131.5,
      "rsi": 65.0,
      "sector_relative": "leader",
      "days_in_phase": 9,
      "previous_phase": "lagging",
      "weight": 3.1
    },
    {
      "id": "MGM",
      "name": "MGM",
      "return_5d": 0.01254,
      "return_20d": 0.00951,
      "volume_ratio": 0.84,
      "momentum_phase": "leading",
      "phase_value": 87.4,
      "phase_delta": 19.6,
      "rs_ratio": 107.1,
      "rs_momentum": 100.4,
      "rsi": 51.5,
      "sector_relative": "leader",
      "days_in_phase": 28,
      "previous_phase": "lagging",
      "weight": 0.8
    },
    {
      "id": "ABNB",
      "name": "ABNB",
      "return_5d": 0.03555,
      "return_20d": 0.02268,
      "volume_ratio": 0.78,
      "momentum_phase": "leading",
      "phase_value": 74.6,
      "phase_delta": -21.8,
      "rs_ratio": 103.8,
      "rs_momentum": 101.1,
      "rsi": 41.3,
      "sector_relative": "leader",
      "days_in_phase": 19,
      "previous_phase": "lagging",
      "weight": 2.6
    },
    {
      "id": "TJX",
      "name": "TJX",
      "return_5d": -0.00483,
      "return_20d": -0.02244,
      "volume_ratio": 0.58,
      "momentum_phase": "leading",
      "phase_value": 45.9,
      "phase_delta": -20.7,
      "rs_ratio": 102.2,
      "rs_momentum": 97.0,
      "rsi": 31.2,
      "sector_relative": "leader",
      "days_in_phase": 27,
      "previous_phase": "lagging",
      "weight": 3.4
    },
    {
      "id": "ORLY",
      "name": "ORLY",
      "return_5d": -0.03965,
      "return_20d": -0.05979,
      "volume_ratio": 0.79,
      "momentum_phase": "leading",
      "phase_value": 36.4,
      "phase_delta": -40.6,
      "rs_ratio": 98.8,
      "rs_momentum": 98.5,
      "rsi": 21.1,
      "sector_relative": "laggard",
      "days_in_phase": 6,
      "previous_phase": "weakening",
      "weight": 2.3
    },
    {
      "id": "DPZ",
      "name": "DPZ",
      "return_5d": -0.06556,
      "return_20d": -0.01928,
      "volume_ratio": 0.89,
      "momentum_phase": "leading",
      "phase_value": 35.7,
      "phase_delta": -59.8,
      "rs_ratio": 98.5,
      "rs_momentum": 98.7,
      "rsi": 36.5,
      "sector_relative": "laggard",
      "days_in_phase": 15,
      "previous_phase": "improving",
      "weight": 1.8
    },
    {
      "id": "GRMN",
      "name": "GRMN",
      "return_5d": 0.00681,
      "return_20d": -0.05178,
      "volume_ratio": 0.8,
      "momentum_phase": "leading",
      "phase_value": 0.0,
      "phase_delta": -50.7,
      "rs_ratio": 101.0,
      "rs_momentum": 85.8,
      "rsi": 28.6,
      "sector_relative": "leader",
      "days_in_phase": 24,
      "previous_phase": "lagging",
      "weight": 0.9
    },
    {
      "id": "CVNA",
      "name": "CVNA",
      "return_5d": -0.01989,
      "return_20d": -0.12608,
      "volume_ratio": 1.29,
      "momentum_phase": "improving",
      "phase_value": 97.3,
      "phase_delta": 59.4,
      "rs_ratio": 96.4,
      "rs_momentum": 113.1,
      "rsi": 35.8,
      "sector_relative": "laggard",
      "days_in_phase": 3,
      "previous_phase": "lagging",
      "weight": 4.2
    },
    {
      "id": "DASH",
      "name": "DASH",
      "return_5d": -0.01301,
      "return_20d": -0.0966,
      "volume_ratio": 1.11,
      "momentum_phase": "improving",
      "phase_value": 43.0,
      "phase_delta": -38.5,
      "rs_ratio": 96.9,
      "rs_momentum": 101.7,
      "rsi": 32.8,
      "sector_relative": "laggard",
      "days_in_phase": 4,
      "previous_phase": "leading",
      "weight": 3.2
    },
    {
      "id": "TSLA",
      "name": "TSLA",
      "return_5d": -0.02786,
      "return_20d": -0.07654,
      "volume_ratio": 1.12,
      "momentum_phase": "improving",
      "phase_value": 38.8,
      "phase_delta": -6.0,
      "rs_ratio": 99.0,
      "rs_momentum": 98.8,
      "rsi": 37.5,
      "sector_relative": "laggard",
      "days_in_phase": 12,
      "previous_phase": "leading",
      "weight": 100.0
    },
    {
      "id": "ROST",
      "name": "ROST",
      "return_5d": 0.02123,
      "return_20d": 0.04794,
      "volume_ratio": 0.73,
      "momentum_phase": "weakening",
      "phase_value": 75.1,
      "phase_delta": -18.5,
      "rs_ratio": 106.2,
      "rs_momentum": 98.8,
      "rsi": 56.2,
      "sector_relative": "leader",
      "days_in_phase": 1,
      "previous_phase": "leading",
      "weight": 2.7
    },
    {
      "id": "SBUX",
      "name": "SBUX",
      "return_5d": -0.03348,
      "return_20d": -0.01703,
      "volume_ratio": 1.29,
      "momentum_phase": "weakening",
      "phase_value": 55.9,
      "phase_delta": -26.9,
      "rs_ratio": 102.2,
      "rs_momentum": 99.0,
      "rsi": 43.9,
      "sector_relative": "laggard",
      "days_in_phase": 20,
      "previous_phase": "leading",
      "weight": 3.5
    },
    {
      "id": "YUM",
      "name": "YUM",
      "return_5d": -0.02587,
      "return_20d": -0.04335,
      "volume_ratio": 0.7,
      "momentum_phase": "weakening",
      "phase_value": 29.9,
      "phase_delta": -16.7,
      "rs_ratio": 100.9,
      "rs_momentum": 95.1,
      "rsi": 29.4,
      "sector_relative": "laggard",
      "days_in_phase": 2,
      "previous_phase": "leading",
      "weight": 1.3
    },
    {
      "id": "MCD",
      "name": "MCD",
      "return_5d": -0.05171,
      "return_20d": -0.05443,
      "volume_ratio": 1.08,
      "momentum_phase": "weakening",
      "phase_value": 12.4,
      "phase_delta": -33.0,
      "rs_ratio": 98.5,
      "rs_momentum": 94.0,
      "rsi": 14.6,
      "sector_relative": "laggard",
      "days_in_phase": 6,
      "previous_phase": "leading",
      "weight": 4.3
    },
    {
      "id": "POOL",
      "name": "POOL",
      "return_5d": -0.01103,
      "return_20d": -0.07238,
      "volume_ratio": 0.78,
      "momentum_phase": "lagging",
      "phase_value": 100.0,
      "phase_delta": 100.0,
      "rs_ratio": 99.8,
      "rs_momentum": 115.3,
      "rsi": 23.4,
      "sector_relative": "laggard",
      "days_in_phase": 18,
      "previous_phase": "weakening",
      "weight": 0.7
    },
    {
      "id": "BBY",
      "name": "BBY",
      "return_5d": 0.02556,
      "return_20d": -0.0045,
      "volume_ratio": 0.64,
      "momentum_phase": "lagging",
      "phase_value": 88.1,
      "phase_delta": 45.6,
      "rs_ratio": 104.9,
      "rs_momentum": 102.7,
      "rsi": 57.3,
      "sector_relative": "leader",
      "days_in_phase": 14,
      "previous_phase": "leading",
      "weight": 1.6
    },
    {
      "id": "WYNN",
      "name": "WYNN",
      "return_5d": 0.02718,
      "return_20d": -0.09998,
      "volume_ratio": 0.5,
      "momentum_phase": "lagging",
      "phase_value": 59.7,
      "phase_delta": 59.7,
      "rs_ratio": 103.2,
      "rs_momentum": 98.7,
      "rsi": 40.2,
      "sector_relative": "leader",
      "days_in_phase": 9,
      "previous_phase": "improving",
      "weight": 1.0
    },
    {
      "id": "LVS",
      "name": "LVS",
      "return_5d": 0.00689,
      "return_20d": -0.06826,
      "volume_ratio": 0.64,
      "momentum_phase": "lagging",
      "phase_value": 56.5,
      "phase_delta": 21.8,
      "rs_ratio": 102.5,
      "rs_momentum": 98.8,
      "rsi": 30.8,
      "sector_relative": "leader",
      "days_in_phase": 7,
      "previous_phase": "leading",
      "weight": 1.0
    },
    {
      "id": "DRI",
      "name": "DRI",
      "return_5d": 0.01013,
      "return_20d": -0.05914,
      "volume_ratio": 2.08,
      "momentum_phase": "lagging",
      "phase_value": 54.2,
      "phase_delta": 48.2,
      "rs_ratio": 102.9,
      "rs_momentum": 97.9,
      "rsi": 39.3,
      "sector_relative": "leader",
      "days_in_phase": 8,
      "previous_phase": "leading",
      "weight": 1.3
    },
    {
      "id": "HLT",
      "name": "HLT",
      "return_5d": 0.02154,
      "return_20d": -0.05694,
      "volume_ratio": 0.66,
      "momentum_phase": "lagging",
      "phase_value": 52.0,
      "phase_delta": 52.0,
      "rs_ratio": 102.2,
      "rs_momentum": 98.2,
      "rsi": 37.7,
      "sector_relative": "leader",
      "days_in_phase": 10,
      "previous_phase": "leading",
      "weight": 2.5
    },
    {
      "id": "GM",
      "name": "GM",
      "return_5d": 0.01934,
      "return_20d": -0.09257,
      "volume_ratio": 0.95,
      "momentum_phase": "lagging",
      "phase_value": 49.0,
      "phase_delta": 25.9,
      "rs_ratio": 100.5,
      "rs_momentum": 99.3,
      "rsi": 29.7,
      "sector_relative": "leader",
      "days_in_phase": 12,
      "previous_phase": "leading",
      "weight": 2.6
    },
    {
      "id": "GPC",
      "name": "GPC",
      "return_5d": -0.06289,
      "return_20d": -0.15299,
      "volume_ratio": 0.76,
      "momentum_phase": "lagging",
      "phase_value": 44.3,
      "phase_delta": 44.3,
      "rs_ratio": 92.8,
      "rs_momentum": 106.0,
      "rsi": 7.5,
      "sector_relative": "laggard",
      "days_in_phase": 19,
      "previous_phase": "leading",
      "weight": 0.8
    },
    {
      "id": "MAR",
      "name": "MAR",
      "return_5d": 0.03531,
      "return_20d": -0.06442,
      "volume_ratio": 0.77,
      "momentum_phase": "lagging",
      "phase_value": 34.6,
      "phase_delta": 34.6,
      "rs_ratio": 102.1,
      "rs_momentum": 94.8,
      "rsi": 38.0,
      "sector_relative": "leader",
      "days_in_phase": 8,
      "previous_phase": "leading",
      "weight": 2.3
    },
    {
      "id": "LULU",
      "name": "LULU",
      "return_5d": 0.04937,
      "return_20d": -0.11602,
      "volume_ratio": 1.3,
      "momentum_phase": "lagging",
      "phase_value": 34.1,
      "phase_delta": 34.1,
      "rs_ratio": 100.7,
      "rs_momentum": 96.1,
      "rsi": 23.1,
      "sector_relative": "leader",
      "days_in_phase": 4,
      "previous_phase": "leading",
      "weight": 2.2
    },
    {
      "id": "RCL",
      "name": "RCL",
      "return_5d": -0.00198,
      "return_20d": -0.13216,
      "volume_ratio": 0.67,
      "momentum_phase": "lagging",
      "phase_value": 30.1,
      "phase_delta": 30.1,
      "rs_ratio": 97.7,
      "rs_momentum": 98.4,
      "rsi": 31.3,
      "sector_relative": "leader",
      "days_in_phase": 15,
      "previous_phase": "leading",
      "weight": 3.3
    },
    {
      "id": "APTV",
      "name": "APTV",
      "return_5d": -0.01887,
      "return_20d": -0.1307,
      "volume_ratio": 0.91,
      "momentum_phase": "lagging",
      "phase_value": 24.3,
      "phase_delta": 24.3,
      "rs_ratio": 98.7,
      "rs_momentum": 96.1,
      "rsi": 33.9,
      "sector_relative": "laggard",
      "days_in_phase": 11,
      "previous_phase": "leading",
      "weight": 0.7
    },
    {
      "id": "WSM",
      "name": "WSM",
      "return_5d": 0.01439,
      "return_20d": -0.15024,
      "volume_ratio": 1.0,
      "momentum_phase": "lagging",
      "phase_value": 20.2,
      "phase_delta": 20.2,
      "rs_ratio": 98.2,
      "rs_momentum": 95.9,
      "rsi": 18.6,
      "sector_relative": "leader",
      "days_in_phase": 11,
      "previous_phase": "weakening",
      "weight": 1.1
    },
    {
      "id": "RL",
      "name": "RL",
      "return_5d": 0.02866,
      "return_20d": -0.11641,
      "volume_ratio": 0.76,
      "momentum_phase": "lagging",
      "phase_value": 17.2,
      "phase_delta": 17.2,
      "rs_ratio": 100.4,
      "rs_momentum": 93.1,
      "rsi": 37.3,
      "sector_relative": "leader",
      "days_in_phase": 7,
      "previous_phase": "leading",
      "weight": 0.9
    },
    {
      "id": "CMG",
      "name": "CMG",
      "return_5d": 0.01292,
      "return_20d": -0.12254,
      "volume_ratio": 0.99,
      "momentum_phase": "lagging",
      "phase_value": 16.4,
      "phase_delta": 16.4,
      "rs_ratio": 97.0,
      "rs_momentum": 96.3,
      "rsi": 28.3,
      "sector_relative": "leader",
      "days_in_phase": 32,
      "previous_phase": "weakening",
      "weight": 2.4
    },
    {
      "id": "TSCO",
      "name": "TSCO",
      "return_5d": -0.02244,
      "return_20d": -0.12412,
      "volume_ratio": 0.79,
      "momentum_phase": "lagging",
      "phase_value": 14.5,
      "phase_delta": 14.5,
      "rs_ratio": 96.0,
      "rs_momentum": 96.9,
      "rsi": 24.5,
      "sector_relative": "laggard",
      "days_in_phase": 9,
      "previous_phase": "leading",
      "weight": 1.2
    },
    {
      "id": "DECK",
      "name": "DECK",
      "return_5d": 0.04098,
      "return_20d": -0.1161,
      "volume_ratio": 0.71,
      "momentum_phase": "lagging",
      "phase_value": 8.7,
      "phase_delta": 8.7,
      "rs_ratio": 100.1,
      "rs_momentum": 91.7,
      "rsi": 23.3,
      "sector_relative": "leader",
      "days_in_phase": 9,
      "previous_phase": "leading",
      "weight": 1.0
    },
    {
      "id": "NVR",
      "name": "NVR",
      "return_5d": -0.00752,
      "return_20d": -0.15338,
      "volume_ratio": 1.02,
      "momentum_phase": "lagging",
      "phase_value": 8.3,
      "phase_delta": 8.3,
      "rs_ratio": 95.6,
      "rs_momentum": 96.0,
      "rsi": 11.1,
      "sector_relative": "leader",
      "days_in_phase": 20,
      "previous_phase": "leading",
      "weight": 0.7
    },
    {
      "id": "HD",
      "name": "HD",
      "return_5d": -0.03191,
      "return_20d": -0.13563,
      "volume_ratio": 0.75,
      "momentum_phase": "lagging",
      "phase_value": 0.7,
      "phase_delta": 0.7,
      "rs_ratio": 95.8,
      "rs_momentum": 94.3,
      "rsi": 13.7,
      "sector_relative": "laggard",
      "days_in_phase": 10,
      "previous_phase": "weakening",
      "weight": 5.9
    },
    {
      "id": "AZO",
      "name": "AZO",
      "return_5d": -0.0621,
      "return_20d": -0.10856,
      "volume_ratio": 0.83,
      "momentum_phase": "lagging",
      "phase_value": 0.0,
      "phase_delta": -32.6,
      "rs_ratio": 95.5,
      "rs_momentum": 92.5,
      "rsi": 30.2,
      "sector_relative": "laggard",
      "days_in_phase": 1,
      "previous_phase": "leading",
      "weight": 2.2
    },
    {
      "id": "CCL",
      "name": "CCL",
      "return_5d": 0.0396,
      "return_20d": -0.22038,
      "volume_ratio": 0.97,
      "momentum_phase": "lagging",
      "phase_value": 0.0,
      "phase_delta": 0.0,
      "rs_ratio": 94.1,
      "rs_momentum": 90.7,
      "rsi": 21.8,
      "sector_relative": "leader",
      "days_in_phase": 11,
      "previous_phase": "leading",
      "weight": 3.0
    },
    {
      "id": "DHI",
      "name": "DHI",
      "return_5d": -0.01787,
      "return_20d": -0.15927,
      "volume_ratio": 0.93,
      "momentum_phase": "lagging",
      "phase_value": 0.0,
      "phase_delta": 0.0,
      "rs_ratio": 96.0,
      "rs_momentum": 89.5,
      "rsi": 14.0,
      "sector_relative": "laggard",
      "days_in_phase": 10,
      "previous_phase": "leading",
      "weight": 1.5
    },
    {
      "id": "F",
      "name": "F",
      "return_5d": -0.00257,
      "return_20d": -0.16916,
      "volume_ratio": 0.72,
      "momentum_phase": "lagging",
      "phase_value": 0.0,
      "phase_delta": 0.0,
      "rs_ratio": 95.1,
      "rs_momentum": 92.0,
      "rsi": 13.9,
      "sector_relative": "leader",
      "days_in_phase": 10,
      "previous_phase": "leading",
      "weight": 3.4
    },
    {
      "id": "HAS",
      "name": "HAS",
      "return_5d": -0.02184,
      "return_20d": -0.09955,
      "volume_ratio": 1.07,
      "momentum_phase": "lagging",
      "phase_value": 0.0,
      "phase_delta": 0.0,
      "rs_ratio": 99.0,
      "rs_momentum": 90.9,
      "rsi": 19.2,
      "sector_relative": "laggard",
      "days_in_phase": 8,
      "previous_phase": "leading",
      "weight": 0.6
    },
    {
      "id": "LEN",
      "name": "LEN",
      "return_5d": -0.01306,
      "return_20d": -0.19526,
      "volume_ratio": 1.07,
      "momentum_phase": "lagging",
      "phase_value": 0.0,
      "phase_delta": 0.0,
      "rs_ratio": 94.0,
      "rs_momentum": 90.6,
      "rsi": 15.2,
      "sector_relative": "laggard",
      "days_in_phase": 10,
      "previous_phase": "weakening",
      "weight": 1.2
    },
    {
      "id": "LOW",
      "name": "LOW",
      "return_5d": -0.03317,
      "return_20d": -0.18066,
      "volume_ratio": 1.24,
      "momentum_phase": "lagging",
      "phase_value": 0.0,
      "phase_delta": 0.0,
      "rs_ratio": 94.5,
      "rs_momentum": 91.7,
      "rsi": 14.1,
      "sector_relative": "laggard",
      "days_in_phase": 13,
      "previous_phase": "weakening",
      "weight": 3.0
    },
    {
      "id": "NKE",
      "name": "NKE",
      "return_5d": -0.01,
      "return_20d": -0.17745,
      "volume_ratio": 0.74,
      "momentum_phase": "lagging",
      "phase_value": 0.0,
      "phase_delta": 0.0,
      "rs_ratio": 95.6,
      "rs_momentum": 89.9,
      "rsi": 10.7,
      "sector_relative": "leader",
      "days_in_phase": 8,
      "previous_phase": "leading",
      "weight": 3.9
    },
    {
      "id": "NCLH",
      "name": "NCLH",
      "return_5d": 0.04081,
      "return_20d": -0.1921,
      "volume_ratio": 0.71,
      "momentum_phase": "lagging",
      "phase_value": 0.0,
      "phase_delta": 0.0,
      "rs_ratio": 95.3,
      "rs_momentum": 87.8,
      "rsi": 22.8,
      "sector_relative": "leader",
      "days_in_phase": 10,
      "previous_phase": "leading",
      "weight": 2.0
    },
    {
      "id": "PHM",
      "name": "PHM",
      "return_5d": -0.00913,
      "return_20d": -0.15654,
      "volume_ratio": 1.1,
      "momentum_phase": "lagging",
      "phase_value": 0.0,
      "phase_delta": 0.0,
      "rs_ratio": 95.6,
      "rs_momentum": 88.5,
      "rsi": 14.6,
      "sector_relative": "leader",
      "days_in_phase": 10,
      "previous_phase": "leading",
      "weight": 0.9
    },
    {
      "id": "TPR",
      "name": "TPR",
      "return_5d": 0.00493,
      "return_20d": -0.08853,
      "volume_ratio": 0.58,
      "momentum_phase": "lagging",
      "phase_value": 0.0,
      "phase_delta": 0.0,
      "rs_ratio": 99.8,
      "rs_momentum": 89.6,
      "rsi": 32.6,
      "sector_relative": "leader",
      "days_in_phase": 7,
      "previous_phase": "leading",
      "weight": 1.3
    },
    {
      "id": "ULTA",
      "name": "ULTA",
      "return_5d": -0.00302,
      "return_20d": -0.21788,
      "volume_ratio": 0.87,
      "momentum_phase": "lagging",
      "phase_value": 0.0,
      "phase_delta": 0.0,
      "rs_ratio": 88.5,
      "rs_momentum": 83.9,
      "rsi": 14.3,
      "sector_relative": "leader",
      "days_in_phase": 8,
      "previous_phase": "leading",
      "weight": 2.0
    }
  ],
  "correlations": [
    {
      "source": "BKNG",
      "target": "EXPE",
      "correlation": 0.939
    },
    {
      "source": "DHI",
      "target": "PHM",
      "correlation": 0.895
    },
    {
      "source": "DHI",
      "target": "LEN",
      "correlation": 0.867
    },
    {
      "source": "NVR",
      "target": "LEN",
      "correlation": 0.86
    },
    {
      "source": "HD",
      "target": "LOW",
      "correlation": 0.854
    },
    {
      "source": "ABNB",
      "target": "DASH",
      "correlation": 0.84
    },
    {
      "source": "CCL",
      "target": "NCLH",
      "correlation": 0.836
    },
    {
      "source": "RCL",
      "target": "CCL",
      "correlation": 0.833
    },
    {
      "source": "LOW",
      "target": "PHM",
      "correlation": 0.833
    },
    {
      "source": "HLT",
      "target": "MAR",
      "correlation": 0.832
    },
    {
      "source": "MAR",
      "target": "CCL",
      "correlation": 0.822
    },
    {
      "source": "CVNA",
      "target": "HLT",
      "correlation": 0.82
    },
    {
      "source": "YUM",
      "target": "MCD",
      "correlation": 0.814
    },
    {
      "source": "CVNA",
      "target": "CMG",
      "correlation": 0.808
    },
    {
      "source": "CCL",
      "target": "NKE",
      "correlation": 0.802
    },
    {
      "source": "WSM",
      "target": "RL",
      "correlation": 0.784
    },
    {
      "source": "MAR",
      "target": "CMG",
      "correlation": 0.783
    },
    {
      "source": "DHI",
      "target": "LOW",
      "correlation": 0.778
    },
    {
      "source": "HLT",
      "target": "CMG",
      "correlation": 0.765
    },
    {
      "source": "WSM",
      "target": "CCL",
      "correlation": 0.764
    }
  ]
}